_accelerate_fft_cffi.abi3.so
accelerate_fft.py
accelerate_fft_build.py
accelerate_fft_test.py
accelerate_fft-0.2.1.dist-info/LICENSE
accelerate_fft-0.2.1.dist-info/METADATA
accelerate_fft-0.2.1.dist-info/WHEEL
accelerate_fft-0.2.1.dist-info/top_level.txt
accelerate_fft-0.2.1.dist-info/RECORD
